ismrpy/__init__.py
ismrpy/main.py
ismrpy-0.2.11.dist-info/LICENSE.txt
ismrpy-0.2.11.dist-info/METADATA
ismrpy-0.2.11.dist-info/WHEEL
ismrpy-0.2.11.dist-info/top_level.txt
ismrpy-0.2.11.dist-info/RECORD
