Metadata-Version: 2.1
Name: ismrpy
Version: 0.2.11
Summary: Reads ismr files and provides pandas data frame
Home-page: https://github.com/dinilbose/ismrpy
Author: Dinil Bose P
Author-email: dinilbose@gmail.com
License: gpl-3.0
Download-URL: https://github.com/dinilbose/ismrpy/archive/0.2.9.tar.gz
Keywords: ismr,pandas
Platform: UNKNOWN
Classifier: Development Status :: 4 - Beta
Classifier: Intended Audience :: Science/Research
Classifier: Topic :: Software Development :: Build Tools
Classifier: License :: OSI Approved :: GNU General Public License v3 or later (GPLv3+)
Classifier: Programming Language :: Python :: 3
Classifier: Programming Language :: Python :: 2.7
Classifier: Programming Language :: Python :: 3.5
Classifier: Programming Language :: Python :: 3.6
Requires-Dist: pandas (>=0.13.1)
